scripts/FastafastqGenerator.py
scripts/__init__.py
scripts/search_ba.py
scripts/search_naive.py
scripts/utils.py
pat_match-1.0.4.dist-info/LICENSE
pat_match-1.0.4.dist-info/METADATA
pat_match-1.0.4.dist-info/WHEEL
pat_match-1.0.4.dist-info/entry_points.txt
pat_match-1.0.4.dist-info/top_level.txt
pat_match-1.0.4.dist-info/RECORD
